orbit/__init__.py
orbit/orbit.py
orbit/orbit_f.py
gemae_orbit-0.4.1.dist-info/METADATA
gemae_orbit-0.4.1.dist-info/WHEEL
gemae_orbit-0.4.1.dist-info/top_level.txt
gemae_orbit-0.4.1.dist-info/RECORD
