Metadata-Version: 2.1
Name: gemae-orbit
Version: 0.4.1
Summary: Orbit object and functional implementations from orbital parameters
Author: Jordi Eguren Brown
Author-email: Jordi Eguren Brown <jordi.eguren.brown@gmail.com>
License: BSD-3-Clause
Keywords: orbit
Classifier: Programming Language :: Python :: 3
Requires-Python: >=3.7
Requires-Dist: astropy
Requires-Dist: numpy
Requires-Dist: pytest
Requires-Dist: pandas
